main.py
llm_explorer/__init__.py
llm_explorer/app.py
llm_explorer/agents/__init__.py
llm_explorer/auth/__init__.py
llm_explorer/chains/__init__.py
llm_explorer/chat/__init__.py
llm_explorer/databases/__init__.py
llm_explorer/databases/adbddl.py
llm_explorer/indexes/__init__.py
llm_explorer/indexes/vectorstore.py
llm_explorer/interfaces/__init__.py
llm_explorer/interfaces/frontend.py
llm_explorer/llm/__init__.py
llm_explorer/templates/__init__.py
llm_explorer/templates/agents.py
llm_explorer/templates/chains.py
llm_explorer/templates/prompt.py
llm_explorer/templates/ui.py
llm_explorer/ui/__init__.py
llm_explorer/ui/lang.py
pages/__init__.py
pages/pandas_agent.py
llm_explorer-0.0.9.dist-info/LICENSE
llm_explorer-0.0.9.dist-info/METADATA
llm_explorer-0.0.9.dist-info/WHEEL
llm_explorer-0.0.9.dist-info/entry_points.txt
llm_explorer-0.0.9.dist-info/top_level.txt
llm_explorer-0.0.9.dist-info/RECORD
