Metadata-Version: 2.1
Name: llm-explorer
Version: 0.0.9
Summary: A Lakehouse LLM Explorer. Wrapper for spark, databricks and langchain processes
Home-page: https://github.com/Occlusion-Solutions/llm_explorer.git
Author: Carlos D. Escobar-Valbuena
Author-email: carlosdavidescobar@gmail.com
Classifier: Programming Language :: Python :: 3
Classifier: License :: OSI Approved :: MIT License
Classifier: Operating System :: OS Independent
Classifier: Development Status :: 3 - Alpha
Classifier: Intended Audience :: Developers
Classifier: Programming Language :: Python :: 3.10
Classifier: Topic :: Software Development :: Libraries :: Python Modules
Requires-Python: >=3.10
License-File: LICENSE
Requires-Dist: streamlit
Requires-Dist: streamlit-chat
Requires-Dist: chromadb
Requires-Dist: pyautogui
Requires-Dist: databricks-sql-connector
Requires-Dist: watchdog
Requires-Dist: psycopg2-binary
Requires-Dist: py4j
Requires-Dist: pyspark
Requires-Dist: build
Requires-Dist: setuptools
Requires-Dist: twine
Requires-Dist: paramiko
Requires-Dist: pydeequ
Requires-Dist: databricks-feature-store
Requires-Dist: Flask
Requires-Dist: Werkzeug
Requires-Dist: pytest
Requires-Dist: responses
Requires-Dist: azure-storage-blob
Requires-Dist: jupyter
Requires-Dist: aiohttp
Requires-Dist: aiosignal
Requires-Dist: altair
Requires-Dist: anyio
Requires-Dist: argilla
Requires-Dist: asn1crypto
Requires-Dist: astroid
Requires-Dist: async-timeout
Requires-Dist: attrs
Requires-Dist: autopep8
Requires-Dist: backoff
Requires-Dist: blinker
Requires-Dist: cachetools
Requires-Dist: cffi
Requires-Dist: charset-normalizer
Requires-Dist: click
Requires-Dist: commonmark
Requires-Dist: cryptography
Requires-Dist: cycler
Requires-Dist: dataclasses-json
Requires-Dist: decorator
Requires-Dist: Deprecated
Requires-Dist: docopt
Requires-Dist: docstring-to-markdown
Requires-Dist: entrypoints
Requires-Dist: et-xmlfile
Requires-Dist: faiss-cpu
Requires-Dist: filelock
Requires-Dist: flake8
Requires-Dist: fonttools
Requires-Dist: frozenlist
Requires-Dist: gitdb
Requires-Dist: GitPython
Requires-Dist: h11
Requires-Dist: httpcore
Requires-Dist: httpx
Requires-Dist: idna
Requires-Dist: importlib-metadata
Requires-Dist: importlib-resources
Requires-Dist: isort
Requires-Dist: Jinja2
Requires-Dist: joblib
Requires-Dist: jsonschema
Requires-Dist: kiwisolver
Requires-Dist: langchain
Requires-Dist: lxml
Requires-Dist: Markdown
Requires-Dist: markdown-it-py
Requires-Dist: MarkupSafe
Requires-Dist: marshmallow
Requires-Dist: marshmallow-enum
Requires-Dist: matplotlib
Requires-Dist: mccabe
Requires-Dist: mdurl
Requires-Dist: monotonic
Requires-Dist: msg-parser
Requires-Dist: multidict
Requires-Dist: mypy-extensions
Requires-Dist: nltk
Requires-Dist: numpy
Requires-Dist: olefile
Requires-Dist: openai
Requires-Dist: openapi-schema-pydantic
Requires-Dist: openpyxl
Requires-Dist: oscrypto
Requires-Dist: pandas
Requires-Dist: Pillow
Requires-Dist: protobuf
Requires-Dist: pyarrow
Requires-Dist: pycodestyle
Requires-Dist: pycparser
Requires-Dist: pycryptodomex
Requires-Dist: pydantic
Requires-Dist: pydeck
Requires-Dist: pydocstyle
Requires-Dist: pyflakes
Requires-Dist: Pygments
Requires-Dist: PyJWT
Requires-Dist: pylint
Requires-Dist: Pympler
Requires-Dist: pyOpenSSL
Requires-Dist: pypandoc
Requires-Dist: pyparsing
Requires-Dist: pyrsistent
Requires-Dist: python-dateutil
Requires-Dist: python-docx
Requires-Dist: python-dotenv
Requires-Dist: python-lsp-jsonrpc
Requires-Dist: python-lsp-server
Requires-Dist: python-magic
Requires-Dist: python-pptx
Requires-Dist: pytoolconfig
Requires-Dist: pytz
Requires-Dist: pytz-deprecation-shim
Requires-Dist: PyYAML
Requires-Dist: regex
Requires-Dist: requests
Requires-Dist: rfc3986
Requires-Dist: rich
Requires-Dist: rope
Requires-Dist: scikit-learn
Requires-Dist: scipy
Requires-Dist: six
Requires-Dist: smmap
Requires-Dist: sniffio
Requires-Dist: snowballstemmer
Requires-Dist: SQLAlchemy
Requires-Dist: sqlparse
Requires-Dist: tenacity
Requires-Dist: threadpoolctl
Requires-Dist: tiktoken
Requires-Dist: toml
Requires-Dist: tomlkit
Requires-Dist: toolz
Requires-Dist: tornado
Requires-Dist: tqdm
Requires-Dist: typing-inspect
Requires-Dist: typing-extensions
Requires-Dist: tzdata
Requires-Dist: tzlocal
Requires-Dist: ujson
Requires-Dist: unstructured
Requires-Dist: urllib3
Requires-Dist: validators
Requires-Dist: whatthepatch
Requires-Dist: wrapt
Requires-Dist: XlsxWriter
Requires-Dist: yapf
Requires-Dist: yarg
Requires-Dist: yarl
Requires-Dist: zipp
Requires-Dist: packaging
Requires-Dist: diffusers
Requires-Dist: accelerate
Requires-Dist: datasets
Requires-Dist: torch
Requires-Dist: soundfile
Requires-Dist: sentencepiece
Requires-Dist: opencv-python
Requires-Dist: sqlalchemy-databricks
Requires-Dist: transformers
Requires-Dist: huggingface-hub
Requires-Dist: streamlit-authenticator
Requires-Dist: tabulate
Requires-Dist: black
